{
    "ACTION_MENU_TOP_LEVEL_LIMIT": {
        "__compat": {
            "mdn_url": "https://developer.mozilla.org/docs/Mozilla/Add-ons/WebExtensions/API/menus/ACTION_MENU_TOP_LEVEL_LIMIT",
            "source_file": "webextensions/api/menus.json",
            "support": {
                "chrome": {
                    "alternative_name": "contextMenus.ACTION_MENU_TOP_LEVEL_LIMIT",
                    "version_added": true
                },
                "edge": {
                    "alternative_name": "contextMenus.ACTION_MENU_TOP_LEVEL_LIMIT",
                    "version_added": true
                },
                "firefox": [
                    {
                        "version_added": "55"
                    },
                    {
                        "alternative_name": "contextMenus.ACTION_MENU_TOP_LEVEL_LIMIT",
                        "version_added": "48"
                    }
                ],
                "firefox_android": {
                    "version_added": false
                },
                "opera": {
                    "alternative_name": "contextMenus.ACTION_MENU_TOP_LEVEL_LIMIT",
                    "version_added": true
                },
                "safari": {
                    "alternative_name": "contextMenus.ACTION_MENU_TOP_LEVEL_LIMIT",
                    "version_added": "14"
                },
                "safari_ios": {
                    "version_added": false
                },
                "thunderbird": {
                    "version_added": true
                }
            }
        }
    },
    "ContextType": {
        "__compat": {
            "mdn_url": "https://developer.mozilla.org/docs/Mozilla/Add-ons/WebExtensions/API/menus/ContextType",
            "source_file": "webextensions/api/menus.json",
            "support": {
                "chrome": {
                    "alternative_name": "contextMenus.ContextType",
                    "version_added": true
                },
                "edge": {
                    "alternative_name": "contextMenus.ContextType",
                    "version_added": true
                },
                "firefox": [
                    {
                        "notes": "'The 'editable' context does not include password fields. Use the 'password' context for this.",
                        "version_added": "55"
                    },
                    {
                        "alternative_name": "contextMenus.ContextType",
                        "version_added": "48"
                    }
                ],
                "firefox_android": {
                    "version_added": false
                },
                "opera": {
                    "alternative_name": "contextMenus.ContextType",
                    "version_added": true
                },
                "safari": {
                    "alternative_name": "contextMenus.ContextType",
                    "version_added": "14"
                },
                "safari_ios": {
                    "version_added": false
                },
                "thunderbird": {
                    "version_added": true
                }
            }
        },
        "action": {
            "__compat": {
                "source_file": "webextensions/api/menus.json",
                "support": {
                    "chrome": {
                        "version_added": true
                    },
                    "edge": {
                        "version_added": true
                    },
                    "firefox": {
                        "version_added": "109"
                    },
                    "firefox_android": {
                        "version_added": false
                    },
                    "opera": {
                        "version_added": true
                    },
                    "safari": {
                        "version_added": false
                    },
                    "safari_ios": {
                        "version_added": false
                    },
                    "thunderbird": {
                        "version_added": "109"
                    }
                }
            }
        },
        "action_menu": {
            "__compat": {
                "support": {
                    "thunderbird": {
                        "version_added": true
                    }
                }
            }
        },
        "all": {
            "__compat": {
                "support": {
                    "thunderbird": {
                        "version_added": true
                    }
                }
            }
        },
        "all_message_attachments": {
            "__compat": {
                "support": {
                    "thunderbird": {
                        "version_added": true
                    }
                }
            }
        },
        "audio": {
            "__compat": {
                "support": {
                    "thunderbird": {
                        "version_added": true
                    }
                }
            }
        },
        "bookmark": {
            "__compat": {
                "source_file": "webextensions/api/menus.json",
                "support": {
                    "chrome": {
                        "impl_url": "https://crbug.com/825443",
                        "version_added": false
                    },
                    "edge": {
                        "impl_url": "https://crbug.com/825443",
                        "version_added": false
                    },
                    "firefox": {
                        "version_added": "59"
                    },
                    "firefox_android": {
                        "version_added": false
                    },
                    "opera": {
                        "impl_url": "https://crbug.com/825443",
                        "version_added": false
                    },
                    "safari": {
                        "version_added": false
                    },
                    "safari_ios": {
                        "version_added": false
                    },
                    "thunderbird": {
                        "version_added": false
                    }
                }
            }
        },
        "browser_action": {
            "__compat": {
                "source_file": "webextensions/api/menus.json",
                "support": {
                    "chrome": {
                        "version_added": true
                    },
                    "edge": {
                        "version_added": true
                    },
                    "firefox": {
                        "notes": "'The 'editable' context does not include password fields. Use the 'password' context for this.",
                        "version_added": "53"
                    },
                    "firefox_android": {
                        "version_added": false
                    },
                    "opera": {
                        "version_added": true
                    },
                    "safari": {
                        "version_added": "14"
                    },
                    "safari_ios": {
                        "version_added": false
                    },
                    "thunderbird": {
                        "version_added": "53"
                    }
                }
            }
        },
        "browser_action_menu": {
            "__compat": {
                "support": {
                    "thunderbird": {
                        "version_added": true
                    }
                }
            }
        },
        "compose_action": {
            "__compat": {
                "support": {
                    "thunderbird": {
                        "version_added": true
                    }
                }
            }
        },
        "compose_action_menu": {
            "__compat": {
                "support": {
                    "thunderbird": {
                        "version_added": true
                    }
                }
            }
        },
        "compose_attachments": {
            "__compat": {
                "support": {
                    "thunderbird": {
                        "version_added": true
                    }
                }
            }
        },
        "compose_body": {
            "__compat": {
                "support": {
                    "thunderbird": {
                        "version_added": true
                    }
                }
            }
        },
        "editable": {
            "__compat": {
                "support": {
                    "thunderbird": {
                        "version_added": true
                    }
                }
            }
        },
        "folder_pane": {
            "__compat": {
                "support": {
                    "thunderbird": {
                        "version_added": true
                    }
                }
            }
        },
        "frame": {
            "__compat": {
                "support": {
                    "thunderbird": {
                        "version_added": true
                    }
                }
            }
        },
        "image": {
            "__compat": {
                "support": {
                    "thunderbird": {
                        "version_added": true
                    }
                }
            }
        },
        "launcher": {
            "__compat": {
                "source_file": "webextensions/api/menus.json",
                "support": {
                    "chrome": {
                        "version_added": true
                    },
                    "edge": {
                        "version_added": true
                    },
                    "firefox": {
                        "version_added": "48"
                    },
                    "firefox_android": {
                        "version_added": false
                    },
                    "opera": {
                        "version_added": true
                    },
                    "safari": {
                        "version_added": false
                    },
                    "safari_ios": {
                        "version_added": false
                    },
                    "thunderbird": {
                        "version_added": false
                    }
                }
            }
        },
        "link": {
            "__compat": {
                "support": {
                    "thunderbird": {
                        "version_added": true
                    }
                }
            }
        },
        "message_attachments": {
            "__compat": {
                "support": {
                    "thunderbird": {
                        "version_added": true
                    }
                }
            }
        },
        "message_display_action": {
            "__compat": {
                "support": {
                    "thunderbird": {
                        "version_added": true
                    }
                }
            }
        },
        "message_display_action_menu": {
            "__compat": {
                "support": {
                    "thunderbird": {
                        "version_added": true
                    }
                }
            }
        },
        "message_list": {
            "__compat": {
                "support": {
                    "thunderbird": {
                        "version_added": true
                    }
                }
            }
        },
        "page": {
            "__compat": {
                "support": {
                    "thunderbird": {
                        "version_added": true
                    }
                }
            }
        },
        "page_action": {
            "__compat": {
                "source_file": "webextensions/api/menus.json",
                "support": {
                    "chrome": {
                        "version_added": true
                    },
                    "edge": {
                        "version_added": true
                    },
                    "firefox": {
                        "version_added": "53"
                    },
                    "firefox_android": {
                        "version_added": false
                    },
                    "opera": {
                        "version_added": true
                    },
                    "safari": {
                        "version_added": "14"
                    },
                    "safari_ios": {
                        "version_added": false
                    },
                    "thunderbird": {
                        "version_added": false
                    }
                }
            }
        },
        "password": {
            "__compat": {
                "source_file": "webextensions/api/menus.json",
                "support": {
                    "chrome": {
                        "version_added": false
                    },
                    "edge": {
                        "version_added": false
                    },
                    "firefox": {
                        "version_added": "53"
                    },
                    "firefox_android": {
                        "version_added": false
                    },
                    "opera": {
                        "version_added": false
                    },
                    "safari": {
                        "version_added": false
                    },
                    "safari_ios": {
                        "version_added": false
                    },
                    "thunderbird": {
                        "version_added": "53"
                    }
                }
            }
        },
        "selection": {
            "__compat": {
                "support": {
                    "thunderbird": {
                        "version_added": true
                    }
                }
            }
        },
        "tab": {
            "__compat": {
                "source_file": "webextensions/api/menus.json",
                "support": {
                    "chrome": {
                        "version_added": false
                    },
                    "edge": {
                        "version_added": false
                    },
                    "firefox": {
                        "version_added": "53"
                    },
                    "firefox_android": {
                        "version_added": false
                    },
                    "opera": {
                        "version_added": false
                    },
                    "safari": {
                        "version_added": false
                    },
                    "safari_ios": {
                        "version_added": false
                    },
                    "thunderbird": {
                        "version_added": "53"
                    }
                }
            }
        },
        "tools_menu": {
            "__compat": {
                "source_file": "webextensions/api/menus.json",
                "support": {
                    "chrome": {
                        "version_added": false
                    },
                    "edge": {
                        "version_added": false
                    },
                    "firefox": {
                        "notes": "Only available at <code>menus.ContextType</code>, not at <code>contextMenus.ContextType</code>.",
                        "version_added": "56"
                    },
                    "firefox_android": {
                        "version_added": false
                    },
                    "opera": {
                        "version_added": false
                    },
                    "safari": {
                        "version_added": false
                    },
                    "safari_ios": {
                        "version_added": false
                    },
                    "thunderbird": {
                        "version_added": "56"
                    }
                }
            }
        },
        "video": {
            "__compat": {
                "support": {
                    "thunderbird": {
                        "version_added": true
                    }
                }
            }
        }
    },
    "ItemType": {
        "__compat": {
            "mdn_url": "https://developer.mozilla.org/docs/Mozilla/Add-ons/WebExtensions/API/menus/ItemType",
            "source_file": "webextensions/api/menus.json",
            "support": {
                "chrome": {
                    "alternative_name": "contextMenus.ItemType",
                    "version_added": true
                },
                "edge": {
                    "alternative_name": "contextMenus.ItemType",
                    "version_added": true
                },
                "firefox": [
                    {
                        "version_added": "55"
                    },
                    {
                        "alternative_name": "contextMenus.ItemType",
                        "version_added": "48"
                    }
                ],
                "firefox_android": {
                    "version_added": false
                },
                "opera": {
                    "alternative_name": "contextMenus.ItemType",
                    "version_added": true
                },
                "safari": {
                    "alternative_name": "contextMenus.ItemType",
                    "version_added": "14"
                },
                "safari_ios": {
                    "version_added": false
                },
                "thunderbird": {
                    "version_added": true
                }
            }
        },
        "checkbox": {
            "__compat": {
                "support": {
                    "thunderbird": {
                        "version_added": true
                    }
                }
            }
        },
        "normal": {
            "__compat": {
                "support": {
                    "thunderbird": {
                        "version_added": true
                    }
                }
            }
        },
        "radio": {
            "__compat": {
                "support": {
                    "thunderbird": {
                        "version_added": true
                    }
                }
            }
        },
        "separator": {
            "__compat": {
                "support": {
                    "thunderbird": {
                        "version_added": true
                    }
                }
            }
        }
    },
    "MenuIconDictionary": {
        "__compat": {
            "support": {
                "thunderbird": {
                    "version_added": true
                }
            }
        }
    },
    "MenuIconPath": {
        "__compat": {
            "support": {
                "thunderbird": {
                    "version_added": true
                }
            }
        }
    },
    "OnClickData": {
        "__compat": {
            "mdn_url": "https://developer.mozilla.org/docs/Mozilla/Add-ons/WebExtensions/API/menus/OnClickData",
            "source_file": "webextensions/api/menus.json",
            "support": {
                "chrome": {
                    "alternative_name": "contextMenus.OnClickData",
                    "version_added": true
                },
                "edge": {
                    "alternative_name": "contextMenus.OnClickData",
                    "version_added": true
                },
                "firefox": [
                    {
                        "version_added": "55"
                    },
                    {
                        "alternative_name": "contextMenus.OnClickData",
                        "version_added": "48"
                    }
                ],
                "firefox_android": {
                    "version_added": false
                },
                "opera": {
                    "alternative_name": "contextMenus.OnClickData",
                    "version_added": true
                },
                "safari": {
                    "alternative_name": "contextMenus.OnClickData",
                    "version_added": "14"
                },
                "safari_ios": {
                    "version_added": false
                },
                "thunderbird": {
                    "version_added": true
                }
            }
        },
        "attachments": {
            "__compat": {
                "support": {
                    "thunderbird": {
                        "version_added": true
                    }
                }
            }
        },
        "bookmarkId": {
            "__compat": {
                "source_file": "webextensions/api/menus.json",
                "support": {
                    "chrome": {
                        "version_added": false
                    },
                    "edge": {
                        "version_added": false
                    },
                    "firefox": {
                        "version_added": "59"
                    },
                    "firefox_android": {
                        "version_added": false
                    },
                    "opera": {
                        "version_added": false
                    },
                    "safari": {
                        "version_added": false
                    },
                    "safari_ios": {
                        "version_added": false
                    },
                    "thunderbird": {
                        "version_added": false
                    }
                }
            }
        },
        "button": {
            "__compat": {
                "source_file": "webextensions/api/menus.json",
                "support": {
                    "chrome": {
                        "version_added": false
                    },
                    "edge": {
                        "version_added": false
                    },
                    "firefox": {
                        "version_added": "64"
                    },
                    "firefox_android": {
                        "version_added": false
                    },
                    "opera": {
                        "version_added": false
                    },
                    "safari": {
                        "version_added": false
                    },
                    "safari_ios": {
                        "version_added": false
                    },
                    "thunderbird": {
                        "version_added": "64"
                    }
                }
            }
        },
        "checked": {
            "__compat": {
                "support": {
                    "thunderbird": {
                        "version_added": true
                    }
                }
            }
        },
        "displayedFolder": {
            "__compat": {
                "support": {
                    "thunderbird": {
                        "version_added": true
                    }
                }
            }
        },
        "editable": {
            "__compat": {
                "support": {
                    "thunderbird": {
                        "version_added": true
                    }
                }
            }
        },
        "fieldId": {
            "__compat": {
                "support": {
                    "thunderbird": {
                        "version_added": true
                    }
                }
            }
        },
        "frameId": {
            "__compat": {
                "source_file": "webextensions/api/menus.json",
                "support": {
                    "chrome": {
                        "alternative_name": "contextMenus.OnClickData.frameId",
                        "version_added": "35"
                    },
                    "edge": {
                        "alternative_name": "contextMenus.OnClickData.frameId",
                        "version_added": "79"
                    },
                    "firefox": {
                        "version_added": "55"
                    },
                    "firefox_android": {
                        "version_added": false
                    },
                    "opera": {
                        "alternative_name": "contextMenus.OnClickData.frameId",
                        "version_added": "22"
                    },
                    "safari": {
                        "alternative_name": "contextMenus.OnClickData.frameId",
                        "version_added": "14"
                    },
                    "safari_ios": {
                        "version_added": false
                    },
                    "thunderbird": {
                        "version_added": "55"
                    }
                }
            }
        },
        "frameUrl": {
            "__compat": {
                "support": {
                    "thunderbird": {
                        "version_added": true
                    }
                }
            }
        },
        "linkText": {
            "__compat": {
                "source_file": "webextensions/api/menus.json",
                "support": {
                    "chrome": {
                        "version_added": false
                    },
                    "edge": {
                        "version_added": false
                    },
                    "firefox": {
                        "version_added": "56"
                    },
                    "firefox_android": {
                        "version_added": false
                    },
                    "opera": {
                        "version_added": false
                    },
                    "safari": {
                        "version_added": false
                    },
                    "safari_ios": {
                        "version_added": false
                    },
                    "thunderbird": {
                        "version_added": "56"
                    }
                }
            }
        },
        "linkUrl": {
            "__compat": {
                "support": {
                    "thunderbird": {
                        "version_added": true
                    }
                }
            }
        },
        "mediaType": {
            "__compat": {
                "support": {
                    "thunderbird": {
                        "version_added": true
                    }
                }
            }
        },
        "menuItemId": {
            "__compat": {
                "support": {
                    "thunderbird": {
                        "version_added": true
                    }
                }
            }
        },
        "modifiers": {
            "__compat": {
                "source_file": "webextensions/api/menus.json",
                "support": {
                    "chrome": {
                        "version_added": false
                    },
                    "edge": {
                        "version_added": false
                    },
                    "firefox": {
                        "version_added": "54"
                    },
                    "firefox_android": {
                        "version_added": false
                    },
                    "opera": {
                        "version_added": false
                    },
                    "safari": {
                        "version_added": false
                    },
                    "safari_ios": {
                        "version_added": false
                    },
                    "thunderbird": {
                        "version_added": "54"
                    }
                }
            }
        },
        "pageUrl": {
            "__compat": {
                "support": {
                    "thunderbird": {
                        "version_added": true
                    }
                }
            }
        },
        "parentMenuItemId": {
            "__compat": {
                "support": {
                    "thunderbird": {
                        "version_added": true
                    }
                }
            }
        },
        "selectedAccount": {
            "__compat": {
                "support": {
                    "thunderbird": {
                        "version_added": true
                    }
                }
            }
        },
        "selectedFolder": {
            "__compat": {
                "support": {
                    "thunderbird": {
                        "version_added": true
                    }
                }
            }
        },
        "selectedFolders": {
            "__compat": {
                "support": {
                    "thunderbird": {
                        "version_added": true
                    }
                }
            }
        },
        "selectedMessages": {
            "__compat": {
                "support": {
                    "thunderbird": {
                        "version_added": true
                    }
                }
            }
        },
        "selectionText": {
            "__compat": {
                "support": {
                    "thunderbird": {
                        "version_added": true
                    }
                }
            }
        },
        "srcUrl": {
            "__compat": {
                "source_file": "webextensions/api/menus.json",
                "support": {
                    "chrome": {
                        "version_added": true
                    },
                    "edge": {
                        "version_added": true
                    },
                    "firefox": {
                        "notes": "Between Firefox 59 and Firefox 94, this returns a post-redirect URL rather than the raw value of the <code>src</code> attribute of the clicked element.",
                        "version_added": "48"
                    },
                    "firefox_android": {
                        "version_added": false
                    },
                    "opera": {
                        "version_added": true
                    },
                    "safari": {
                        "version_added": "14"
                    },
                    "safari_ios": {
                        "version_added": false
                    },
                    "thunderbird": {
                        "version_added": "48"
                    }
                }
            }
        },
        "targetElementId": {
            "__compat": {
                "source_file": "webextensions/api/menus.json",
                "support": {
                    "chrome": {
                        "version_added": false
                    },
                    "edge": {
                        "version_added": false
                    },
                    "firefox": {
                        "version_added": "63"
                    },
                    "firefox_android": {
                        "version_added": false
                    },
                    "opera": {
                        "version_added": false
                    },
                    "safari": {
                        "version_added": false
                    },
                    "safari_ios": {
                        "version_added": false
                    },
                    "thunderbird": {
                        "version_added": "63"
                    }
                }
            }
        },
        "viewType": {
            "__compat": {
                "support": {
                    "thunderbird": {
                        "version_added": true
                    }
                }
            }
        },
        "wasChecked": {
            "__compat": {
                "support": {
                    "thunderbird": {
                        "version_added": true
                    }
                }
            }
        }
    },
    "OnShowData": {
        "__compat": {
            "support": {
                "thunderbird": {
                    "version_added": true
                }
            }
        }
    },
    "__compat": {
        "mdn_url": "https://developer.mozilla.org/docs/Mozilla/Add-ons/WebExtensions/API/menus",
        "source_file": "webextensions/api/menus.json",
        "support": {
            "chrome": {
                "alternative_name": "contextMenus",
                "version_added": true
            },
            "edge": {
                "alternative_name": "contextMenus",
                "version_added": true
            },
            "firefox": [
                {
                    "version_added": "55"
                },
                {
                    "alternative_name": "contextMenus",
                    "version_added": "48"
                }
            ],
            "firefox_android": {
                "version_added": false
            },
            "opera": {
                "alternative_name": "contextMenus",
                "version_added": true
            },
            "safari": {
                "alternative_name": "contextMenus",
                "version_added": "14"
            },
            "safari_ios": {
                "version_added": false
            },
            "thunderbird": {
                "version_added": true
            }
        }
    },
    "create": {
        "__compat": {
            "mdn_url": "https://developer.mozilla.org/docs/Mozilla/Add-ons/WebExtensions/API/menus/create",
            "source_file": "webextensions/api/menus.json",
            "support": {
                "chrome": {
                    "alternative_name": "contextMenus.create",
                    "notes": "Items that don't specify 'contexts' do not inherit contexts from their parents.",
                    "version_added": true
                },
                "edge": {
                    "alternative_name": "contextMenus.create",
                    "notes": "Items that don't specify 'contexts' do not inherit contexts from their parents.",
                    "version_added": true
                },
                "firefox": [
                    {
                        "version_added": "55"
                    },
                    {
                        "alternative_name": "contextMenus.create",
                        "notes": "Before version 53, items that don't specify 'contexts' do not inherit contexts from their parents.",
                        "version_added": "48"
                    }
                ],
                "firefox_android": {
                    "version_added": false
                },
                "opera": {
                    "alternative_name": "contextMenus.create",
                    "notes": "Items that don't specify 'contexts' do not inherit contexts from their parents.",
                    "version_added": true
                },
                "safari": {
                    "alternative_name": "contextMenus.create",
                    "notes": "Items that don't specify 'contexts' do not inherit contexts from their parents.",
                    "version_added": "14"
                },
                "safari_ios": {
                    "version_added": false
                },
                "thunderbird": {
                    "version_added": true
                }
            }
        },
        "accessKey": {
            "__compat": {
                "description": "<code>&amp;</code> in <code>title</code> sets access key",
                "source_file": "webextensions/api/menus.json",
                "support": {
                    "chrome": {
                        "version_added": true
                    },
                    "edge": {
                        "version_added": true
                    },
                    "firefox": {
                        "version_added": "63"
                    },
                    "firefox_android": {
                        "version_added": false
                    },
                    "opera": {
                        "version_added": true
                    },
                    "safari": {
                        "notes": "Safari removes <code>&amp;</code> from menu items' displayed titles, but does not support invoking menu items via access keys.",
                        "partial_implementation": true,
                        "version_added": "14"
                    },
                    "safari_ios": {
                        "version_added": false
                    },
                    "thunderbird": {
                        "version_added": "63"
                    }
                }
            }
        },
        "checked": {
            "__compat": {
                "support": {
                    "thunderbird": {
                        "version_added": true
                    }
                }
            }
        },
        "command": {
            "__compat": {
                "source_file": "webextensions/api/menus.json",
                "support": {
                    "chrome": {
                        "version_added": false
                    },
                    "edge": {
                        "version_added": false
                    },
                    "firefox": {
                        "version_added": "55"
                    },
                    "firefox_android": {
                        "version_added": false
                    },
                    "opera": {
                        "version_added": false
                    },
                    "safari": {
                        "version_added": false
                    },
                    "safari_ios": {
                        "version_added": false
                    },
                    "thunderbird": {
                        "version_added": "55"
                    }
                }
            },
            "_execute_action": {
                "__compat": {
                    "support": {
                        "thunderbird": {
                            "version_added": true
                        }
                    }
                }
            },
            "_execute_browser_action": {
                "__compat": {
                    "support": {
                        "thunderbird": {
                            "version_added": true
                        }
                    }
                }
            },
            "_execute_compose_action": {
                "__compat": {
                    "support": {
                        "thunderbird": {
                            "version_added": true
                        }
                    }
                }
            },
            "_execute_message_display_action": {
                "__compat": {
                    "support": {
                        "thunderbird": {
                            "version_added": true
                        }
                    }
                }
            },
            "_execute_page_action": {
                "__compat": {
                    "support": {
                        "thunderbird": {
                            "version_added": false
                        }
                    }
                }
            },
            "_execute_sidebar_action": {
                "__compat": {
                    "support": {
                        "thunderbird": {
                            "version_added": false
                        }
                    }
                }
            }
        },
        "contexts": {
            "__compat": {
                "support": {
                    "thunderbird": {
                        "version_added": true
                    }
                }
            }
        },
        "createProperties": {
            "__compat": {
                "support": {
                    "thunderbird": {
                        "version_added": true
                    }
                }
            }
        },
        "documentUrlPatterns": {
            "__compat": {
                "support": {
                    "thunderbird": {
                        "version_added": true
                    }
                }
            }
        },
        "enabled": {
            "__compat": {
                "support": {
                    "thunderbird": {
                        "version_added": true
                    }
                }
            }
        },
        "icons": {
            "__compat": {
                "source_file": "webextensions/api/menus.json",
                "support": {
                    "chrome": {
                        "version_added": false
                    },
                    "edge": {
                        "version_added": false
                    },
                    "firefox": {
                        "version_added": "56"
                    },
                    "firefox_android": {
                        "version_added": false
                    },
                    "opera": {
                        "version_added": false
                    },
                    "safari": {
                        "version_added": false
                    },
                    "safari_ios": {
                        "version_added": false
                    },
                    "thunderbird": {
                        "version_added": "56"
                    }
                }
            }
        },
        "id": {
            "__compat": {
                "support": {
                    "thunderbird": {
                        "version_added": true
                    }
                }
            }
        },
        "onclick": {
            "__compat": {
                "support": {
                    "thunderbird": {
                        "version_added": true
                    }
                }
            },
            "info": {
                "__compat": {
                    "support": {
                        "thunderbird": {
                            "version_added": true
                        }
                    }
                },
                "bookmarkId": {
                    "__compat": {
                        "support": {
                            "thunderbird": {
                                "version_added": false
                            }
                        }
                    }
                }
            },
            "tab": {
                "__compat": {
                    "support": {
                        "thunderbird": {
                            "version_added": true
                        }
                    }
                },
                "attention": {
                    "__compat": {
                        "support": {
                            "thunderbird": {
                                "version_added": false
                            }
                        }
                    }
                },
                "audible": {
                    "__compat": {
                        "support": {
                            "thunderbird": {
                                "version_added": false
                            }
                        }
                    }
                },
                "autoDiscardable": {
                    "__compat": {
                        "support": {
                            "thunderbird": {
                                "version_added": false
                            }
                        }
                    }
                },
                "discarded": {
                    "__compat": {
                        "support": {
                            "thunderbird": {
                                "version_added": false
                            }
                        }
                    }
                },
                "hidden": {
                    "__compat": {
                        "support": {
                            "thunderbird": {
                                "version_added": false
                            }
                        }
                    }
                },
                "incognito": {
                    "__compat": {
                        "support": {
                            "thunderbird": {
                                "version_added": false
                            }
                        }
                    }
                },
                "isArticle": {
                    "__compat": {
                        "support": {
                            "thunderbird": {
                                "version_added": false
                            }
                        }
                    }
                },
                "isInReaderMode": {
                    "__compat": {
                        "support": {
                            "thunderbird": {
                                "version_added": false
                            }
                        }
                    }
                },
                "lastAccessed": {
                    "__compat": {
                        "support": {
                            "thunderbird": {
                                "version_added": false
                            }
                        }
                    }
                },
                "mutedInfo": {
                    "__compat": {
                        "support": {
                            "thunderbird": {
                                "version_added": false
                            }
                        }
                    }
                },
                "openerTabId": {
                    "__compat": {
                        "support": {
                            "thunderbird": {
                                "version_added": false
                            }
                        }
                    }
                },
                "pinned": {
                    "__compat": {
                        "support": {
                            "thunderbird": {
                                "version_added": false
                            }
                        }
                    }
                },
                "selected": {
                    "__compat": {
                        "support": {
                            "thunderbird": {
                                "version_added": false
                            }
                        }
                    }
                },
                "sessionId": {
                    "__compat": {
                        "support": {
                            "thunderbird": {
                                "version_added": false
                            }
                        }
                    }
                },
                "sharingState": {
                    "__compat": {
                        "support": {
                            "thunderbird": {
                                "version_added": false
                            }
                        }
                    }
                },
                "successorTabId": {
                    "__compat": {
                        "support": {
                            "thunderbird": {
                                "version_added": false
                            }
                        }
                    }
                }
            }
        },
        "parentId": {
            "__compat": {
                "support": {
                    "thunderbird": {
                        "version_added": true
                    }
                }
            }
        },
        "targetUrlPatterns": {
            "__compat": {
                "support": {
                    "thunderbird": {
                        "version_added": true
                    }
                }
            }
        },
        "title": {
            "__compat": {
                "support": {
                    "thunderbird": {
                        "version_added": true
                    }
                }
            }
        },
        "type": {
            "__compat": {
                "support": {
                    "thunderbird": {
                        "version_added": true
                    }
                }
            }
        },
        "viewTypes": {
            "__compat": {
                "support": {
                    "thunderbird": {
                        "version_added": true
                    }
                }
            }
        },
        "visible": {
            "__compat": {
                "source_file": "webextensions/api/menus.json",
                "support": {
                    "chrome": {
                        "version_added": "62"
                    },
                    "edge": {
                        "version_added": "79"
                    },
                    "firefox": {
                        "version_added": "63"
                    },
                    "firefox_android": {
                        "version_added": false
                    },
                    "opera": {
                        "version_added": "49"
                    },
                    "safari": {
                        "version_added": "14"
                    },
                    "safari_ios": {
                        "version_added": false
                    },
                    "thunderbird": {
                        "version_added": "63"
                    }
                }
            }
        }
    },
    "getTargetElement": {
        "__compat": {
            "mdn_url": "https://developer.mozilla.org/docs/Mozilla/Add-ons/WebExtensions/API/menus/getTargetElement",
            "source_file": "webextensions/api/menus.json",
            "support": {
                "chrome": {
                    "version_added": false
                },
                "edge": {
                    "version_added": false
                },
                "firefox": {
                    "version_added": "63"
                },
                "firefox_android": {
                    "version_added": false
                },
                "opera": {
                    "version_added": false
                },
                "safari": {
                    "version_added": false
                },
                "safari_ios": {
                    "version_added": false
                },
                "thunderbird": {
                    "version_added": "63"
                }
            }
        },
        "targetElementId": {
            "__compat": {
                "support": {
                    "thunderbird": {
                        "version_added": true
                    }
                }
            }
        }
    },
    "onClicked": {
        "__compat": {
            "mdn_url": "https://developer.mozilla.org/docs/Mozilla/Add-ons/WebExtensions/API/menus/onClicked",
            "source_file": "webextensions/api/menus.json",
            "support": {
                "chrome": {
                    "alternative_name": "contextMenus.onClicked",
                    "version_added": true
                },
                "edge": {
                    "alternative_name": "contextMenus.onClicked",
                    "version_added": true
                },
                "firefox": [
                    {
                        "version_added": "55"
                    },
                    {
                        "alternative_name": "contextMenus.onClicked",
                        "version_added": "48"
                    }
                ],
                "firefox_android": {
                    "version_added": false
                },
                "opera": {
                    "alternative_name": "contextMenus.onClicked",
                    "version_added": true
                },
                "safari": {
                    "alternative_name": "contextMenus.onClicked",
                    "version_added": "14"
                },
                "safari_ios": {
                    "version_added": false
                },
                "thunderbird": {
                    "version_added": true
                }
            }
        },
        "info": {
            "__compat": {
                "support": {
                    "thunderbird": {
                        "version_added": true
                    }
                }
            },
            "bookmarkId": {
                "__compat": {
                    "support": {
                        "thunderbird": {
                            "version_added": false
                        }
                    }
                }
            }
        },
        "tab": {
            "__compat": {
                "support": {
                    "thunderbird": {
                        "version_added": true
                    }
                }
            },
            "attention": {
                "__compat": {
                    "support": {
                        "thunderbird": {
                            "version_added": false
                        }
                    }
                }
            },
            "audible": {
                "__compat": {
                    "support": {
                        "thunderbird": {
                            "version_added": false
                        }
                    }
                }
            },
            "autoDiscardable": {
                "__compat": {
                    "support": {
                        "thunderbird": {
                            "version_added": false
                        }
                    }
                }
            },
            "discarded": {
                "__compat": {
                    "support": {
                        "thunderbird": {
                            "version_added": false
                        }
                    }
                }
            },
            "hidden": {
                "__compat": {
                    "support": {
                        "thunderbird": {
                            "version_added": false
                        }
                    }
                }
            },
            "incognito": {
                "__compat": {
                    "support": {
                        "thunderbird": {
                            "version_added": false
                        }
                    }
                }
            },
            "isArticle": {
                "__compat": {
                    "support": {
                        "thunderbird": {
                            "version_added": false
                        }
                    }
                }
            },
            "isInReaderMode": {
                "__compat": {
                    "support": {
                        "thunderbird": {
                            "version_added": false
                        }
                    }
                }
            },
            "lastAccessed": {
                "__compat": {
                    "support": {
                        "thunderbird": {
                            "version_added": false
                        }
                    }
                }
            },
            "mutedInfo": {
                "__compat": {
                    "support": {
                        "thunderbird": {
                            "version_added": false
                        }
                    }
                }
            },
            "openerTabId": {
                "__compat": {
                    "support": {
                        "thunderbird": {
                            "version_added": false
                        }
                    }
                }
            },
            "pinned": {
                "__compat": {
                    "support": {
                        "thunderbird": {
                            "version_added": false
                        }
                    }
                }
            },
            "selected": {
                "__compat": {
                    "support": {
                        "thunderbird": {
                            "version_added": false
                        }
                    }
                }
            },
            "sessionId": {
                "__compat": {
                    "support": {
                        "thunderbird": {
                            "version_added": false
                        }
                    }
                }
            },
            "sharingState": {
                "__compat": {
                    "support": {
                        "thunderbird": {
                            "version_added": false
                        }
                    }
                }
            },
            "successorTabId": {
                "__compat": {
                    "support": {
                        "thunderbird": {
                            "version_added": false
                        }
                    }
                }
            }
        }
    },
    "onHidden": {
        "__compat": {
            "mdn_url": "https://developer.mozilla.org/docs/Mozilla/Add-ons/WebExtensions/API/menus/onHidden",
            "source_file": "webextensions/api/menus.json",
            "support": {
                "chrome": {
                    "version_added": false
                },
                "edge": {
                    "version_added": false
                },
                "firefox": [
                    {
                        "version_added": "60"
                    },
                    {
                        "alternative_name": "contextMenus.onHidden",
                        "version_added": "60"
                    }
                ],
                "firefox_android": {
                    "version_added": false
                },
                "opera": {
                    "version_added": false
                },
                "safari": {
                    "version_added": false
                },
                "safari_ios": {
                    "version_added": false
                },
                "thunderbird": {
                    "version_added": true
                }
            }
        }
    },
    "onShown": {
        "__compat": {
            "mdn_url": "https://developer.mozilla.org/docs/Mozilla/Add-ons/WebExtensions/API/menus/onShown",
            "source_file": "webextensions/api/menus.json",
            "support": {
                "chrome": {
                    "version_added": false
                },
                "edge": {
                    "version_added": false
                },
                "firefox": [
                    {
                        "version_added": "60"
                    },
                    {
                        "alternative_name": "contextMenus.onShown",
                        "version_added": "60"
                    }
                ],
                "firefox_android": {
                    "version_added": false
                },
                "opera": {
                    "version_added": false
                },
                "safari": {
                    "version_added": false
                },
                "safari_ios": {
                    "version_added": false
                },
                "thunderbird": {
                    "version_added": true
                }
            }
        },
        "info": {
            "__compat": {
                "support": {
                    "thunderbird": {
                        "version_added": true
                    }
                }
            }
        },
        "tab": {
            "__compat": {
                "support": {
                    "thunderbird": {
                        "version_added": true
                    }
                }
            },
            "attention": {
                "__compat": {
                    "support": {
                        "thunderbird": {
                            "version_added": false
                        }
                    }
                }
            },
            "audible": {
                "__compat": {
                    "support": {
                        "thunderbird": {
                            "version_added": false
                        }
                    }
                }
            },
            "autoDiscardable": {
                "__compat": {
                    "support": {
                        "thunderbird": {
                            "version_added": false
                        }
                    }
                }
            },
            "discarded": {
                "__compat": {
                    "support": {
                        "thunderbird": {
                            "version_added": false
                        }
                    }
                }
            },
            "hidden": {
                "__compat": {
                    "support": {
                        "thunderbird": {
                            "version_added": false
                        }
                    }
                }
            },
            "incognito": {
                "__compat": {
                    "support": {
                        "thunderbird": {
                            "version_added": false
                        }
                    }
                }
            },
            "isArticle": {
                "__compat": {
                    "support": {
                        "thunderbird": {
                            "version_added": false
                        }
                    }
                }
            },
            "isInReaderMode": {
                "__compat": {
                    "support": {
                        "thunderbird": {
                            "version_added": false
                        }
                    }
                }
            },
            "lastAccessed": {
                "__compat": {
                    "support": {
                        "thunderbird": {
                            "version_added": false
                        }
                    }
                }
            },
            "mutedInfo": {
                "__compat": {
                    "support": {
                        "thunderbird": {
                            "version_added": false
                        }
                    }
                }
            },
            "openerTabId": {
                "__compat": {
                    "support": {
                        "thunderbird": {
                            "version_added": false
                        }
                    }
                }
            },
            "pinned": {
                "__compat": {
                    "support": {
                        "thunderbird": {
                            "version_added": false
                        }
                    }
                }
            },
            "selected": {
                "__compat": {
                    "support": {
                        "thunderbird": {
                            "version_added": false
                        }
                    }
                }
            },
            "sessionId": {
                "__compat": {
                    "support": {
                        "thunderbird": {
                            "version_added": false
                        }
                    }
                }
            },
            "sharingState": {
                "__compat": {
                    "support": {
                        "thunderbird": {
                            "version_added": false
                        }
                    }
                }
            },
            "successorTabId": {
                "__compat": {
                    "support": {
                        "thunderbird": {
                            "version_added": false
                        }
                    }
                }
            }
        }
    },
    "overrideContext": {
        "__compat": {
            "mdn_url": "https://developer.mozilla.org/docs/Mozilla/Add-ons/WebExtensions/API/menus/overrideContext",
            "source_file": "webextensions/api/menus.json",
            "support": {
                "chrome": {
                    "version_added": false
                },
                "edge": {
                    "version_added": false
                },
                "firefox": {
                    "version_added": "64"
                },
                "firefox_android": {
                    "version_added": false
                },
                "opera": {
                    "version_added": false
                },
                "safari": {
                    "version_added": false
                },
                "safari_ios": {
                    "version_added": false
                },
                "thunderbird": {
                    "version_added": "64"
                }
            }
        },
        "contextOptions": {
            "__compat": {
                "support": {
                    "thunderbird": {
                        "version_added": true
                    }
                }
            },
            "bookmarkId": {
                "__compat": {
                    "support": {
                        "thunderbird": {
                            "version_added": false
                        }
                    }
                }
            },
            "context": {
                "__compat": {
                    "support": {
                        "thunderbird": {
                            "version_added": true
                        }
                    }
                },
                "bookmark": {
                    "__compat": {
                        "support": {
                            "thunderbird": {
                                "version_added": false
                            }
                        }
                    }
                }
            }
        }
    },
    "refresh": {
        "__compat": {
            "mdn_url": "https://developer.mozilla.org/docs/Mozilla/Add-ons/WebExtensions/API/menus/refresh",
            "source_file": "webextensions/api/menus.json",
            "support": {
                "chrome": {
                    "version_added": false
                },
                "edge": {
                    "version_added": false
                },
                "firefox": [
                    {
                        "version_added": "60"
                    },
                    {
                        "alternative_name": "contextMenus.refresh",
                        "version_added": "60"
                    }
                ],
                "firefox_android": {
                    "version_added": false
                },
                "opera": {
                    "version_added": false
                },
                "safari": {
                    "version_added": false
                },
                "safari_ios": {
                    "version_added": false
                },
                "thunderbird": {
                    "version_added": true
                }
            }
        }
    },
    "remove": {
        "__compat": {
            "mdn_url": "https://developer.mozilla.org/docs/Mozilla/Add-ons/WebExtensions/API/menus/remove",
            "source_file": "webextensions/api/menus.json",
            "support": {
                "chrome": {
                    "alternative_name": "contextMenus.remove",
                    "version_added": true
                },
                "edge": {
                    "alternative_name": "contextMenus.remove",
                    "version_added": true
                },
                "firefox": [
                    {
                        "version_added": "55"
                    },
                    {
                        "alternative_name": "contextMenus.remove",
                        "version_added": "48"
                    }
                ],
                "firefox_android": {
                    "version_added": false
                },
                "opera": {
                    "alternative_name": "contextMenus.remove",
                    "version_added": true
                },
                "safari": {
                    "alternative_name": "contextMenus.remove",
                    "version_added": "14"
                },
                "safari_ios": {
                    "version_added": false
                },
                "thunderbird": {
                    "version_added": true
                }
            }
        },
        "menuItemId": {
            "__compat": {
                "support": {
                    "thunderbird": {
                        "version_added": true
                    }
                }
            }
        }
    },
    "removeAll": {
        "__compat": {
            "mdn_url": "https://developer.mozilla.org/docs/Mozilla/Add-ons/WebExtensions/API/menus/removeAll",
            "source_file": "webextensions/api/menus.json",
            "support": {
                "chrome": {
                    "alternative_name": "contextMenus.removeAll",
                    "version_added": true
                },
                "edge": {
                    "alternative_name": "contextMenus.removeAll",
                    "version_added": true
                },
                "firefox": [
                    {
                        "version_added": "55"
                    },
                    {
                        "alternative_name": "contextMenus.removeAll",
                        "version_added": "48"
                    }
                ],
                "firefox_android": {
                    "version_added": false
                },
                "opera": {
                    "alternative_name": "contextMenus.removeAll",
                    "version_added": true
                },
                "safari": {
                    "alternative_name": "contextMenus.removeAll",
                    "version_added": "14"
                },
                "safari_ios": {
                    "version_added": false
                },
                "thunderbird": {
                    "version_added": true
                }
            }
        }
    },
    "update": {
        "__compat": {
            "mdn_url": "https://developer.mozilla.org/docs/Mozilla/Add-ons/WebExtensions/API/menus/update",
            "source_file": "webextensions/api/menus.json",
            "support": {
                "chrome": {
                    "alternative_name": "contextMenus.update",
                    "version_added": true
                },
                "edge": {
                    "alternative_name": "contextMenus.update",
                    "version_added": true
                },
                "firefox": [
                    {
                        "version_added": "55"
                    },
                    {
                        "alternative_name": "contextMenus.update",
                        "version_added": "48"
                    }
                ],
                "firefox_android": {
                    "version_added": false
                },
                "opera": {
                    "alternative_name": "contextMenus.update",
                    "version_added": true
                },
                "safari": {
                    "alternative_name": "contextMenus.update",
                    "version_added": "14"
                },
                "safari_ios": {
                    "version_added": false
                },
                "thunderbird": {
                    "version_added": true
                }
            }
        },
        "id": {
            "__compat": {
                "support": {
                    "thunderbird": {
                        "version_added": true
                    }
                }
            }
        },
        "updateProperties": {
            "__compat": {
                "support": {
                    "thunderbird": {
                        "version_added": true
                    }
                }
            },
            "onclick": {
                "__compat": {
                    "support": {
                        "thunderbird": {
                            "version_added": true
                        }
                    }
                },
                "info": {
                    "__compat": {
                        "support": {
                            "thunderbird": {
                                "version_added": true
                            }
                        }
                    },
                    "bookmarkId": {
                        "__compat": {
                            "support": {
                                "thunderbird": {
                                    "version_added": false
                                }
                            }
                        }
                    }
                },
                "tab": {
                    "__compat": {
                        "support": {
                            "thunderbird": {
                                "version_added": true
                            }
                        }
                    },
                    "attention": {
                        "__compat": {
                            "support": {
                                "thunderbird": {
                                    "version_added": false
                                }
                            }
                        }
                    },
                    "audible": {
                        "__compat": {
                            "support": {
                                "thunderbird": {
                                    "version_added": false
                                }
                            }
                        }
                    },
                    "autoDiscardable": {
                        "__compat": {
                            "support": {
                                "thunderbird": {
                                    "version_added": false
                                }
                            }
                        }
                    },
                    "discarded": {
                        "__compat": {
                            "support": {
                                "thunderbird": {
                                    "version_added": false
                                }
                            }
                        }
                    },
                    "hidden": {
                        "__compat": {
                            "support": {
                                "thunderbird": {
                                    "version_added": false
                                }
                            }
                        }
                    },
                    "incognito": {
                        "__compat": {
                            "support": {
                                "thunderbird": {
                                    "version_added": false
                                }
                            }
                        }
                    },
                    "isArticle": {
                        "__compat": {
                            "support": {
                                "thunderbird": {
                                    "version_added": false
                                }
                            }
                        }
                    },
                    "isInReaderMode": {
                        "__compat": {
                            "support": {
                                "thunderbird": {
                                    "version_added": false
                                }
                            }
                        }
                    },
                    "lastAccessed": {
                        "__compat": {
                            "support": {
                                "thunderbird": {
                                    "version_added": false
                                }
                            }
                        }
                    },
                    "mutedInfo": {
                        "__compat": {
                            "support": {
                                "thunderbird": {
                                    "version_added": false
                                }
                            }
                        }
                    },
                    "openerTabId": {
                        "__compat": {
                            "support": {
                                "thunderbird": {
                                    "version_added": false
                                }
                            }
                        }
                    },
                    "pinned": {
                        "__compat": {
                            "support": {
                                "thunderbird": {
                                    "version_added": false
                                }
                            }
                        }
                    },
                    "selected": {
                        "__compat": {
                            "support": {
                                "thunderbird": {
                                    "version_added": false
                                }
                            }
                        }
                    },
                    "sessionId": {
                        "__compat": {
                            "support": {
                                "thunderbird": {
                                    "version_added": false
                                }
                            }
                        }
                    },
                    "sharingState": {
                        "__compat": {
                            "support": {
                                "thunderbird": {
                                    "version_added": false
                                }
                            }
                        }
                    },
                    "successorTabId": {
                        "__compat": {
                            "support": {
                                "thunderbird": {
                                    "version_added": false
                                }
                            }
                        }
                    }
                }
            }
        }
    }
}